qichang/__init__.py
qichang/openai_api_key.pkl
qichang/qichang-computer.py
qichang/qichang.py
qichang-0.0.59.dist-info/LICENSE
qichang-0.0.59.dist-info/METADATA
qichang-0.0.59.dist-info/PKG-INFO-computer
qichang-0.0.59.dist-info/WHEEL
qichang-0.0.59.dist-info/top_level.txt
qichang-0.0.59.dist-info/RECORD
