Metadata-Version: 2.1
Name: qichang
Version: 0.0.59
Summary: A Python library for interacting with various language model APIs
Home-page: https://github.com/QichangZheng/qichang.git
Author: Qichang Zheng
Author-email: qichangzheng@uchicago.edu
License: Apache License 2.0
Keywords: language models API client
Classifier: Development Status :: 3 - Alpha
Classifier: Intended Audience :: Developers
Classifier: Topic :: Software Development :: Libraries :: Python Modules
Classifier: License :: OSI Approved :: Apache Software License
Classifier: Programming Language :: Python :: 3
Classifier: Programming Language :: Python :: 3.7
Classifier: Programming Language :: Python :: 3.8
Classifier: Programming Language :: Python :: 3.9
Classifier: Programming Language :: Python :: 3.10
Classifier: Programming Language :: Python :: 3.11
Requires-Python: >=3.7
License-File: LICENSE
Requires-Dist: requests
Requires-Dist: ping3
Requires-Dist: bs4
Requires-Dist: tqdm
Requires-Dist: openai ==1.5.0
Requires-Dist: func-timeout
